dj_chart/__init__.py
dj_chart/constants.py
dj_chart/models.py
dj_chart/urls.py
dj_chart/views.py
dj_chart/static/js/Chart.min.js
dj_chart/templates/chart.html
dj_chart-1.1.10.dist-info/AUTHORS.rst
dj_chart-1.1.10.dist-info/LICENSE
dj_chart-1.1.10.dist-info/METADATA
dj_chart-1.1.10.dist-info/WHEEL
dj_chart-1.1.10.dist-info/top_level.txt
dj_chart-1.1.10.dist-info/RECORD
