Metadata-Version: 2.1
Name: dj-chart
Version: 1.1.10
Summary: Create Charts with the awesome Chart.js Library
Home-page: https://gitlab.com/systent/dj_chart
Author: Robert Dollinger
Author-email: robert.d@systent.it
License: BSD
Keywords: dj_chart
Platform: UNKNOWN
Classifier: Development Status :: 5 - Production/Stable
Classifier: Framework :: Django
Classifier: Framework :: Django :: 1.8
Classifier: Framework :: Django :: 1.9
Classifier: Framework :: Django :: 1.10
Classifier: Intended Audience :: Developers
Classifier: License :: OSI Approved :: BSD License
Classifier: Natural Language :: English
Classifier: Programming Language :: Python :: 3
Classifier: Programming Language :: Python :: 3.2
Classifier: Programming Language :: Python :: 3.3
Classifier: Programming Language :: Python :: 3.4
Classifier: Programming Language :: Python :: 3.5
Requires-Dist: django (>=1.10)
Requires-Dist: python-dateutil (>=2.6)
